{
	"_payitem_id_0": "_payitem_id_0",
	"length_limit_scale_______": "length_limit_scale_______",
	"length_limit_scale___________": "length_limit_scale___________",
	"length_limit_scale____________|||__________________________________________": "length_limit_scale____________|||__________________________________________",
	"_payitem_id_1": "_payitem_id_1",
	"燃料パック250": "燃料包250",
	"補給のお供！燃料パック\n(燃料を250回復させます)": "補給專用! 燃料包!\n(回復+250燃料)",
	"_same": "_same",
	"_payitem_id_2": "_payitem_id_2",
	"弾薬パック250": "彈藥包(250)",
	"補給のお供！弾薬パック\n(弾薬を250回復させます)": "補給專用! 彈藥包!\n(回復+250彈藥)",
	"_same": "_same",
	"_payitem_id_3": "_payitem_id_3",
	"鋼材パック200": "鋼材包200",
	"艦の建造に！鋼材パック\n(鋼材を200回復させます)": "建造船隻!鋼材包\n(回復+200鋼材)",
	"_same": "_same",
	"_payitem_id_4": "_payitem_id_4",
	"ボーキサイトパック150": "鋁土包150",
	"航空機関連にボーキサイトパッ\nク(ボーキサイトを150回復さ\nせます)": "與航空機相關的鋁土\n(回復+150鋁土)",
	"航空機関連にボーキサイトパック\n(ボーキサイトを150回復させます)": "與航空機相關的鋁土\n(回復+150鋁土)",
	"_payitem_id_5": "_payitem_id_5",
	"開発資材パック7": "開發資材包7",
	"建造・開発をバリバリどうぞ！\n開発資材パック(7回分)": "用於建造・開發，請收下\n開發資材(7回份)",
	"_same": "_same",
	"_payitem_id_6": "_payitem_id_6",
	"高速建造材パック6": "高速建造材包6",
	"建造時間を劇的に短縮！\n高速建造材パック(6回分)": "大大縮短建造時間！\n高速建造材包(6回份)",
	"_same": "_same",
	"_payitem_id_7": "_payitem_id_7",
	"高速修復材パック6": "高速修復材包6",
	"修理、お待たせしません！\n高速修復材パック(6回分)": "修理，無需等待！\n高速修復材包(6回份)",
	"_same": "_same",
	"_payitem_id_8": "_payitem_id_8",
	"お買得！工廠セット": "超值！工廠套組",
	"お買得！工廠セット(鋼1500，\nボ200，弾200，燃200，開発\n資材3)": "超值！工廠套組(鋼1500，\n鋁200，彈200，燃200，開發\n資材3)",
	"お買得！工廠セット(鋼1500，ボ200，弾200，燃200，開発資材3)": "超值！工廠套組(鋼1500，鋁200，彈200，燃200，開發資材3)",
	"_payitem_id_9": "_payitem_id_9",
	"お買得！出撃セット": "超值！出擊套組",
	"お買得！出撃セット(燃500，\n弾500，鋼200，高速修復材3)": "超值！出擊套組(燃500，\n彈500，鋼200，高速修復材3)",
	"お買得！出撃セット(燃500，弾500，鋼200，高速修復材3)": "超值！出擊套組(燃500，彈500，鋼200，高速修復材3)",
	"_payitem_id_10": "_payitem_id_10",
	"ドック増設セット": "渠位增設套組",
	"ドック増設セット(鍵1，開発資\n材6，高速建造6，高速修復6)": "渠位增設套組(鑰匙1，開發資\n材6，高速建造6，高速修復6)",
	"ドック増設セット(鍵1，開発資材\n6，高速建造6，高速修復6)": "渠位增設套組(鑰匙1，開發資材6，\n高速建造6，高速修復6)",
	"_payitem_id_11": "_payitem_id_11",
	"応急修理要員(TL in equipment)": "損害管制人員",
	"大切な艦を轟沈から護ります！\n応急修理要員(1回分)": "防止艦船轟沈！\n損害管制人員(一回份)",
	"_same": "_same",
	"_payitem_id_12": "_payitem_id_12",
	"ダメコン特盛セット": "損害管制人員特別套組",
	"期間限定！ダメコン特盛セット(応急修理女神2，応急修理要員3)": "期間限定！ 損害管制人員特別套組 (損害管制女神2，損害管制人員3)",
	"_same": "_same",
	"_payitem_id_13": "_payitem_id_13",
	"八八資源セット": "八八資源套組",
	"期間限定！八八資源セット(燃\n880，弾880，鋼880，ボ\n880)": "期間限定！八八資源套組(燃\n880，彈880，鋼880，鋁\n880)",
	"期間限定！八八資源セット(燃\n880，弾880，鋼880，ボ880)": "期間限定！八八資源套組(燃\n880，彈880，鋼880，鋁880)",
	"_payitem_id_14": "_payitem_id_14",
	"応急修理女神(TL in equipment)": "損害管制女神",
	"轟沈を防ぎ耐久補給全回復！\n応急修理女神(1回分)": "防止轟沈，耐久補給全回復！\n損害管制女神(一回份)",
	"_same": "_same",
	"_payitem_id_15": "_payitem_id_15",
	"特注家具職人(TL in normal items)": "特注家具職人",
	"特注家具を製作できます！\n特注家具職人(1回分)": "可製作特別家具！\n特注家具職人(1回份)",
	"_same": "_same",
	"_payitem_id_16": "_payitem_id_16",
	"母港拡張(TL in normal items)": "母港擴張",
	"母港拡張 艦隊の艦娘保有数を\n+10隻分拡張できます！\n※ご注意※ 最大計500隻まで！\n装備枠も自動的に+40増加しま\nす。": "母港擴張 艦隊艦娘保有數\n+10隻！\n※注意※最大500隻！\n裝備欄位也會自動\n+40。",
	"母港拡張 艦隊の艦娘保有数を+10隻分拡張できます！\n※ご注意※ 最大計500隻まで！ 装備枠も自動的に+40増加します。": "母港擴張 艦隊艦娘保有數\n+10隻！\n※注意※最大500隻！\n裝備欄位也會自動+40。",
	"_payitem_id_17": "_payitem_id_17",
	"タンカー徴用": "徵用油輪",
	"油の一滴は…燃料不足解消に！\nタンカー徴用(燃1200)": "一滴油...解決燃油不足！\n徵用油輪(燃1200)",
	"_same": "_same",
	"_payitem_id_18": "_payitem_id_18",
	"給糧艦「間宮」(TL in normal items)": "給糧艦「間宮」",
	"給糧艦「間宮」召喚 艦娘の疲れ\nた心を食糧や甘味でたちまち回\n復(1艦隊1回分)": "召喚給糧艦「間宮」，用甜蜜的點心\n回復艦娘疲憊的心(1艦隊1回份)",
	"給糧艦「間宮」召喚 艦娘の疲れた心を食糧や甘味でたちまち回復(1艦隊1回分)": "召喚給糧艦「間宮」，用甜蜜的點心\n回復艦娘疲憊的心(1艦隊1回份)",
	"_payitem_id_19": "_payitem_id_19",
	"アルミ大量産": "鋁土大增產",
	"ジュラルミンは航空機の源！\nアルミ大増産(ボ650)": "杜拉鋁是航空機的源頭！\n鋁土大增產(鋁650)",
	"_same": "_same",
	"_payitem_id_20": "_payitem_id_20",
	"書類一式＆指輪(TL in normal items)": "書類一式 & 戒指",
	"レベルが99になった艦娘とケッ\nコンカッコカリ！\n書類一式＆指輪(1回分)": "與等級99的艦娘結婚(假)！\n書類一式 & 戒指(一回份)",
	"レベルが99になった艦娘とケッコンカッコカリ！\n書類一式＆指輪(1回分)": "與等級99的艦娘結婚(假)！\n書類一式 & 戒指(一回份)",
	"_payitem_id_21": "_payitem_id_21",
	"艦娘へのクッキー": "給艦娘的餅乾",
	"ホワイトデー特別アイテム、\n「艦娘へのクッキー」 ※「間\n宮」券付！　\n(鋼材314，ボーキ314，開発\n資材2)": "白色情人節的特別物品\n「艦娘的餅乾」※附贈間宮券\n鋼材314，鋁314，開發資材2)",
	"ホワイトデー特別アイテム、「艦娘\nへのクッキー」 ※「間宮」券付！": "白色情人節的特別物品\n「艦娘的餅乾」※附贈間宮券\n鋼材314，鋁314，開發資材2)",
	"_payitem_id_22": "_payitem_id_22",
	"改修資材パック10": "改修資材包10",
	"明石さんの「改修工廠」で、装\n備を改修します。\n(改修資材10)": "用於明石「改修工廠」裝備\n改修。\n(改修資材10)",
	"明石さんの「改修工廠」で、装備を改修します。\n(改修資材10)": "用於明石「改修工廠」裝備\n改修。\n(改修資材10)",
	"_payitem_id_23": "_payitem_id_23",
	"給糧艦「伊良湖」5": "給糧艦「伊良湖」5",
	"給糧艦「伊良湖」召喚 甘いスイ\nーツで何人かの艦娘の気分がた\nちまち高揚！(5回分)": "召喚給糧艦「伊良湖」，這樣的甜點，\n任何吃下的艦娘都會提升士氣\n！(5回份)",
	"給糧艦「伊良湖」召喚 甘いスイーツで何人かの艦娘の気分がたちまち高揚！(5回分)": "召喚給糧艦「伊良湖」，這樣的甜點，\n任何吃下的艦娘都會提升士氣\n！(5回份)",
	"_payitem_id_24": "_payitem_id_24",
	"戦闘糧食(TL in equipment)": "戰鬥糧食",
	"激しい戦闘のお供に心尽くしの\n「戦闘糧食」をどうぞ！(3回分)": "為激烈戰鬥提供的\n「戰鬥糧食」！(3回份)",
	"激しい戦闘のお供に心尽くしの「戦闘糧食」をどうぞ！(3回分)": "為激烈戰鬥提供的\n「戰鬥糧食」！(3回份)",
	"_payitem_id_25": "_payitem_id_25",
	"洋上補給(TL in equipment)": "洋上補給",
	"使用には「給油艦/補給艦」の\n運用が必要です。(2回分)": "使用需要「給油艦/補給艦」\n(2回份)",
	"使用には「給油艦/補給艦」の運用が必要です。(2回分)": "使用需要「給油艦/補給艦」\n(2回份)",
	"_payitem_id_26": "_payitem_id_26",
	"補強増設(TL in normal items)": "補強增設",
	"練度30以上の艦娘を補強増設改\n修できます。(1回分)": "給練度30以上的艦娘進行補強增設\n改修。(1回份)",
	"練度30以上の艦娘を補強増設改修できます。(1回分)": "給練度30以上的艦娘進行補強增設\n改修。(1回份)",
	"_payitem_id_27": "_payitem_id_27",
	"設営隊(TL in normal items)": "設營隊",
	"飛行場などの設営/拡張に必要\nです。\n(※最大計10個まで保有可能)": "飛行場設營/擴張必需。\n(最多保有10個)",
	"飛行場などの設営/拡張に必要です。\n(※最大計10個まで保有可能)": "飛行場設營/擴張必需。\n(最多保有10個)",
	"_payitem_id_28": "_payitem_id_28",
	"「緊急修理資材」セット": "「緊急修理資材」套組",
	"工作艦などの艦で緊急泊地修理\nを実施するための資材セット。\n※緊急修理資材×３\n(使用には工作艦等が必要です)※鉄鋼800": "工作艦等實施緊急泊地修理的\n資材套組。\n※緊急修理資材×３\n(使用需要工作艦)※鋼800",
	"工作艦などの艦で緊急泊地修理を実施するための資材セット。\n※緊急修理資材×３(使用には工作艦等が必要です)※鉄鋼800": "工作艦等實施緊急泊地修理的\n資材套組。\n※緊急修理資材×３\n(使用需要工作艦)※鋼800",
	"_payitem_id_29": "_payitem_id_29",
	"潜水艦補給物資パック": "潛水艦補給物資包",
	"潜水母艦＆潜水艦2隻以上の \n「潜水艦隊攻撃」を行う補給\n物資セット。　※潜水艦補給\n物資×３(一か所の潜水艦隊\n攻撃で一つ消費します)": "潛水母艦 & 潛水艦2隻以上的\n「潛水艦隊攻擊」的物資補給套組。※潜水艦補給物資×３\n(潛水艦隊攻擊一次消費一個)",
	"潜水母艦＆潜水艦2隻以上の「潜水艦隊攻撃」を行う補給物資セット。\n※潜水艦補給物資×３(一か所の潜水艦隊攻撃で一つ消費します)": "潛水母艦 & 潛水艦2隻以上的\n「潛水艦隊攻擊」的物資補給套組。※潜水艦補給物資×３\n(潛水艦隊攻擊一次消費一個)",

	"dummy": "forNoComma"
}